Metadata-Version: 2.1
Name: my_package_test_for_learn
Version: 0.1.1
Summary: A simple example Python package
Home-page: https://github.com/GauravKaklotar/my_package
Author: Gaurav Kaklotar
Author-email: gauravkaklotar2003@gmail.com
Classifier: Programming Language :: Python :: 3
Classifier: License :: OSI Approved :: MIT License
Classifier: Operating System :: OS Independent
Requires-Python: >=3.6
